{
  "kind": "coverage_report",
  "version": "1.0",
  "generatedAt": "2026-02-11T02:39:27.999Z",
  "sources": {
    "buildRequest": true,
    "implementationPlan": true
  },
  "requirements": {
    "total": 1,
    "implemented": 0,
    "items": [
      {
        "id": "REQ-9",
        "summary": "Update the backend listing creation logic in `backend/main.mo` so that whenever a new `Listing` record is created, it explicitly sets `propertyStatus = #available`. Ensure this is applied to every code path that constructs and stores a new `Listing` (including user/owner-created listings, public submissions that become listings, and any demo/seed listing creation if present).",
        "status": "unknown",
        "plannedFiles": [],
        "matchedFiles": []
      }
    ]
  },
  "changedFiles": [
    "backend/main.mo",
    "build-request.json",
    "feature_evidence.json",
    "frontend-implementation-plan.json",
    "frontend/src/backend.d.ts",
    "frontend/src/backend.ts",
    "frontend/src/declarations/backend.did.d.ts",
    "frontend/src/declarations/backend.did.js",
    "project_state.json",
    "scratch/component-selection.json",
    "spec.md",
    "spec_vs_diff_report.json"
  ]
}